Workbook

Sheet P&L
A1: GAMMA — Management P&L (Cash Basis)
A2: Jan–May 2026 actuals · KGS · capital expenditure, owner drawings and capital injections are excluded (shown in Cash Flow).
C4: Jan-26 | D4: Feb-26 | E4: Mar-26 | F4: Apr-26 | G4: May-26 | H4: YTD
A5: REVENUE
A6: Retail sales (POS + cash) | C6: =SUMIF(Data!$A:$A,"REV_RETAIL",Data!$D:$D) -> 2696575.7 | D6: =SUMIF(Data!$A:$A,"REV_RETAIL",Data!$E:$E) -> 2680292.6 | E6: =SUMIF(Data!$A:$A,"REV_RETAIL",Data!$F:$F) -> 3786003.5 | F6: =SUMIF(Data!$A:$A,"REV_RETAIL",Data!$G:$G) -> 5118052.6 | G6: =SUMIF(Data!$A:$A,"REV_RETAIL",Data!$H:$H) -> 5797503.9 | H6: =SUM(C6:G6) -> 20078428
A7: Wholesale (B2B) | C7: =SUMIF(Data!$A:$A,"REV_B2B",Data!$D:$D) -> 776585.4 | D7: =SUMIF(Data!$A:$A,"REV_B2B",Data!$E:$E) -> 645280.7 | E7: =SUMIF(Data!$A:$A,"REV_B2B",Data!$F:$F) -> 1890097.9 | F7: =SUMIF(Data!$A:$A,"REV_B2B",Data!$G:$G) -> 1102775.4 | G7: =SUMIF(Data!$A:$A,"REV_B2B",Data!$H:$H) -> 1752000.7 | H7: =SUM(C7:G7) -> 6166740.1
A8: Other operating income (sublease, recycling) | C8: =SUMIF(Data!$A:$A,"REV_OTHER",Data!$D:$D) -> 21000 | D8: =SUMIF(Data!$A:$A,"REV_OTHER",Data!$E:$E) -> 17155 | E8: =SUMIF(Data!$A:$A,"REV_OTHER",Data!$F:$F) -> 308075 | F8: =SUMIF(Data!$A:$A,"REV_OTHER",Data!$G:$G) -> 25600 | G8: =SUMIF(Data!$A:$A,"REV_OTHER",Data!$H:$H) -> 37377 | H8: =SUM(C8:G8) -> 409207
A9: Total revenue | C9: =C6+C7+C8 -> 3494161.1 | D9: =D6+D7+D8 -> 3342728.3 | E9: =E6+E7+E8 -> 5984176.4 | F9: =F6+F7+F8 -> 6246427.9 | G9: =G6+G7+G8 -> 7586881.6 | H9: =SUM(C9:G9) -> 26654375
A11: COST OF SALES
A12: Goods purchased (supplier payments) | C12: =SUMIF(Data!$A:$A,"COGS_SUP",Data!$D:$D) -> 1930393.5 | D12: =SUMIF(Data!$A:$A,"COGS_SUP",Data!$E:$E) -> 2685411.3 | E12: =SUMIF(Data!$A:$A,"COGS_SUP",Data!$F:$F) -> 3278858.5 | F12: =SUMIF(Data!$A:$A,"COGS_SUP",Data!$G:$G) -> 3948901.8 | G12: =SUMIF(Data!$A:$A,"COGS_SUP",Data!$H:$H) -> 2558170.1 | H12: =SUM(C12:G12) -> 14401735
A13: Import, customs, logistics & broker | C13: =SUMIF(Data!$A:$A,"COGS_IMPORT",Data!$D:$D) -> 24093 | D13: =SUMIF(Data!$A:$A,"COGS_IMPORT",Data!$E:$E) -> 2041700.7 | E13: =SUMIF(Data!$A:$A,"COGS_IMPORT",Data!$F:$F) -> 622040 | F13: =SUMIF(Data!$A:$A,"COGS_IMPORT",Data!$G:$G) -> 48800 | G13: =SUMIF(Data!$A:$A,"COGS_IMPORT",Data!$H:$H) -> 1569799.8 | H13: =SUM(C13:G13) -> 4306433.5
A14: Total cost of sales | C14: =C12+C13 -> 1954486.5 | D14: =D12+D13 -> 4727112 | E14: =E12+E13 -> 3900898.5 | F14: =F12+F13 -> 3997701.8 | G14: =G12+G13 -> 4127969.9 | H14: =SUM(C14:G14) -> 18708169
A16: GROSS PROFIT | C16: =C9-C14 -> 1539674.6 | D16: =D9-D14 -> -1384383.7 | E16: =E9-E14 -> 2083277.9 | F16: =F9-F14 -> 2248726.1 | G16: =G9-G14 -> 3458911.7 | H16: =SUM(C16:G16) -> 7946206.6
A17: Gross margin % | C17: =IF(C9=0,0,C16/C9) -> 0.44064214 | D17: =IF(D9=0,0,D16/D9) -> -0.41414785 | E17: =IF(E9=0,0,E16/E9) -> 0.3481311 | F17: =IF(F9=0,0,F16/F9) -> 0.36000193 | G17: =IF(G9=0,0,G16/G9) -> 0.4559069 | H17: =IF(H9=0,0,H16/H9) -> 0.29812016
A19: OPERATING EXPENSES
A20: Personnel (payroll, taxes, social) | C20: =SUMIF(Data!$A:$A,"OPEX_PAYROLL",Data!$D:$D) -> 652355 | D20: =SUMIF(Data!$A:$A,"OPEX_PAYROLL",Data!$E:$E) -> 721554.41 | E20: =SUMIF(Data!$A:$A,"OPEX_PAYROLL",Data!$F:$F) -> 847586.51 | F20: =SUMIF(Data!$A:$A,"OPEX_PAYROLL",Data!$G:$G) -> 1027262.9 | G20: =SUMIF(Data!$A:$A,"OPEX_PAYROLL",Data!$H:$H) -> 1121320 | H20: =SUM(C20:G20) -> 4370078.9
A21: Rent & utilities | C21: =SUMIF(Data!$A:$A,"OPEX_RENT",Data!$D:$D) -> 69601.59 | D21: =SUMIF(Data!$A:$A,"OPEX_RENT",Data!$E:$E) -> 62454.74 | E21: =SUMIF(Data!$A:$A,"OPEX_RENT",Data!$F:$F) -> 60442.98 | F21: =SUMIF(Data!$A:$A,"OPEX_RENT",Data!$G:$G) -> 29852.02 | G21: =SUMIF(Data!$A:$A,"OPEX_RENT",Data!$H:$H) -> 41506.97 | H21: =SUM(C21:G21) -> 263858.3
A22: Marketing & transport | C22: =SUMIF(Data!$A:$A,"OPEX_MKT",Data!$D:$D) -> 20000 | D22: =SUMIF(Data!$A:$A,"OPEX_MKT",Data!$E:$E) -> 2400 | E22: =SUMIF(Data!$A:$A,"OPEX_MKT",Data!$F:$F) -> 69486 | F22: =SUMIF(Data!$A:$A,"OPEX_MKT",Data!$G:$G) -> 80237 | G22: =SUMIF(Data!$A:$A,"OPEX_MKT",Data!$H:$H) -> 55814 | H22: =SUM(C22:G22) -> 227937
A23: Bank charges & commissions | C23: =SUMIF(Data!$A:$A,"OPEX_BANK",Data!$D:$D) -> 35150.97 | D23: =SUMIF(Data!$A:$A,"OPEX_BANK",Data!$E:$E) -> 23119.07 | E23: =SUMIF(Data!$A:$A,"OPEX_BANK",Data!$F:$F) -> 31670.83 | F23: =SUMIF(Data!$A:$A,"OPEX_BANK",Data!$G:$G) -> 53610.61 | G23: =SUMIF(Data!$A:$A,"OPEX_BANK",Data!$H:$H) -> 47713.27 | H23: =SUM(C23:G23) -> 191264.75
A24: Services & subscriptions | C24: =SUMIF(Data!$A:$A,"OPEX_SERV",Data!$D:$D) -> 41300 | D24: =SUMIF(Data!$A:$A,"OPEX_SERV",Data!$E:$E) -> 112422 | E24: =SUMIF(Data!$A:$A,"OPEX_SERV",Data!$F:$F) -> 50809 | F24: =SUMIF(Data!$A:$A,"OPEX_SERV",Data!$G:$G) -> 45126.62 | G24: =SUMIF(Data!$A:$A,"OPEX_SERV",Data!$H:$H) -> 10180 | H24: =SUM(C24:G24) -> 259837.62
A25: Market consumables | C25: =SUMIF(Data!$A:$A,"OPEX_CONS",Data!$D:$D) -> 6950 | D25: =SUMIF(Data!$A:$A,"OPEX_CONS",Data!$E:$E) -> 36155 | E25: =SUMIF(Data!$A:$A,"OPEX_CONS",Data!$F:$F) -> 4180 | F25: =SUMIF(Data!$A:$A,"OPEX_CONS",Data!$G:$G) -> 5530 | G25: =SUMIF(Data!$A:$A,"OPEX_CONS",Data!$H:$H) -> 1760 | H25: =SUM(C25:G25) -> 54575
A26: Total operating expenses | C26: =C20+C21+C22+C23+C24+C25 -> 825357.56 | D26: =D20+D21+D22+D23+D24+D25 -> 958105.22 | E26: =E20+E21+E22+E23+E24+E25 -> 1064175.3 | F26: =F20+F21+F22+F23+F24+F25 -> 1241619.2 | G26: =G20+G21+G22+G23+G24+G25 -> 1278294.3 | H26: =SUM(C26:G26) -> 5367551.5
A28: EBITDA | C28: =C16-C26 -> 714317.08 | D28: =D16-D26 -> -2342488.9 | E28: =E16-E26 -> 1019102.6 | F28: =F16-F26 -> 1007107 | G28: =G16-G26 -> 2180617.4 | H28: =SUM(C28:G28) -> 2578655.1
A29: EBITDA margin % | C29: =IF(C9=0,0,C28/C9) -> 0.20443164 | D29: =IF(D9=0,0,D28/D9) -> -0.70077157 | E29: =IF(E9=0,0,E28/E9) -> 0.17029955 | F29: =IF(F9=0,0,F28/F9) -> 0.16122926 | G29: =IF(G9=0,0,G28/G9) -> 0.28741946 | H29: =IF(H9=0,0,H28/H9) -> 0.096744158
A30: Unified (simplified) tax | C30: =SUMIF(Data!$A:$A,"TAX",Data!$D:$D) -> 92671 | D30: =SUMIF(Data!$A:$A,"TAX",Data!$E:$E) -> 100020 | E30: =SUMIF(Data!$A:$A,"TAX",Data!$F:$F) -> 248968.44 | F30: =SUMIF(Data!$A:$A,"TAX",Data!$G:$G) -> 145209.77 | G30: =SUMIF(Data!$A:$A,"TAX",Data!$H:$H) -> 154846.41 | H30: =SUM(C30:G30) -> 741715.62
A31: Operating profit (EBIT) | C31: =C28-C30 -> 621646.08 | D31: =D28-D30 -> -2442508.9 | E31: =E28-E30 -> 770134.14 | F31: =F28-F30 -> 861897.21 | G31: =G28-G30 -> 2025771 | H31: =SUM(C31:G31) -> 1836939.5
A33: NON-OPERATING
A34: Other non-operating (travel, fines, advances) | C34: =SUMIF(Data!$A:$A,"NONOP_OTHER",Data!$D:$D) -> 0 | D34: =SUMIF(Data!$A:$A,"NONOP_OTHER",Data!$E:$E) -> 20000 | E34: =SUMIF(Data!$A:$A,"NONOP_OTHER",Data!$F:$F) -> 5000 | F34: =SUMIF(Data!$A:$A,"NONOP_OTHER",Data!$G:$G) -> 152000 | G34: =SUMIF(Data!$A:$A,"NONOP_OTHER",Data!$H:$H) -> 25000 | H34: =SUM(C34:G34) -> 202000
A35: Unclassified payments (marked '?') | C35: =SUMIF(Data!$A:$A,"NONOP_UNCL",Data!$D:$D) -> 0 | D35: =SUMIF(Data!$A:$A,"NONOP_UNCL",Data!$E:$E) -> 131660 | E35: =SUMIF(Data!$A:$A,"NONOP_UNCL",Data!$F:$F) -> 9600 | F35: =SUMIF(Data!$A:$A,"NONOP_UNCL",Data!$G:$G) -> 2120 | G35: =SUMIF(Data!$A:$A,"NONOP_UNCL",Data!$H:$H) -> 660 | H35: =SUM(C35:G35) -> 144040
A37: NET PROFIT (cash basis) | C37: =C31-C34-C35 -> 621646.08 | D37: =D31-D34-D35 -> -2594168.9 | E37: =E31-E34-E35 -> 755534.14 | F37: =F31-F34-F35 -> 707777.21 | G37: =G31-G34-G35 -> 2000111 | H37: =SUM(C37:G37) -> 1490899.5
A38: Net margin % | C38: =IF(C9=0,0,C37/C9) -> 0.17790996 | D38: =IF(D9=0,0,D37/D9) -> -0.77606336 | E38: =IF(E9=0,0,E37/E9) -> 0.12625532 | F38: =IF(F9=0,0,F37/F9) -> 0.11330911 | G38: =IF(G9=0,0,G37/G9) -> 0.26362755 | H38: =IF(H9=0,0,H37/H9) -> 0.055934512
A40: Memo — excluded from P&L above (see Cash Flow): capital expenditure, owner drawings, and capital injections.

Sheet Cash Flow
A1: GAMMA — Cash Flow Statement (Cash Basis)
A2: Jan–May 2026 actuals · KGS · ties to the source file's net-cash line.
C4: Jan-26 | D4: Feb-26 | E4: Mar-26 | F4: Apr-26 | G4: May-26 | H4: YTD
A5: OPERATING ACTIVITIES
A6: Cash receipts from customers & other income | C6: =SUMIF(Data!$A:$A,"REV_RETAIL",Data!$D:$D)+SUMIF(Data!$A:$A,"REV_B2B",Data!$D:$D)+SUMIF(Data!$A:$A,"REV_OTHER",Data!$D:$D) -> 3494161.1 | D6: =SUMIF(Data!$A:$A,"REV_RETAIL",Data!$E:$E)+SUMIF(Data!$A:$A,"REV_B2B",Data!$E:$E)+SUMIF(Data!$A:$A,"REV_OTHER",Data!$E:$E) -> 3342728.3 | E6: =SUMIF(Data!$A:$A,"REV_RETAIL",Data!$F:$F)+SUMIF(Data!$A:$A,"REV_B2B",Data!$F:$F)+SUMIF(Data!$A:$A,"REV_OTHER",Data!$F:$F) -> 5984176.4 | F6: =SUMIF(Data!$A:$A,"REV_RETAIL",Data!$G:$G)+SUMIF(Data!$A:$A,"REV_B2B",Data!$G:$G)+SUMIF(Data!$A:$A,"REV_OTHER",Data!$G:$G) -> 6246427.9 | G6: =SUMIF(Data!$A:$A,"REV_RETAIL",Data!$H:$H)+SUMIF(Data!$A:$A,"REV_B2B",Data!$H:$H)+SUMIF(Data!$A:$A,"REV_OTHER",Data!$H:$H) -> 7586881.6 | H6: =SUM(C6:G6) -> 26654375
A7: Payments to suppliers (goods) | C7: =-SUMIF(Data!$A:$A,"COGS_SUP",Data!$D:$D) -> -1930393.5 | D7: =-SUMIF(Data!$A:$A,"COGS_SUP",Data!$E:$E) -> -2685411.3 | E7: =-SUMIF(Data!$A:$A,"COGS_SUP",Data!$F:$F) -> -3278858.5 | F7: =-SUMIF(Data!$A:$A,"COGS_SUP",Data!$G:$G) -> -3948901.8 | G7: =-SUMIF(Data!$A:$A,"COGS_SUP",Data!$H:$H) -> -2558170.1 | H7: =SUM(C7:G7) -> -14401735
A8: Import, customs, logistics & broker | C8: =-SUMIF(Data!$A:$A,"COGS_IMPORT",Data!$D:$D) -> -24093 | D8: =-SUMIF(Data!$A:$A,"COGS_IMPORT",Data!$E:$E) -> -2041700.7 | E8: =-SUMIF(Data!$A:$A,"COGS_IMPORT",Data!$F:$F) -> -622040 | F8: =-SUMIF(Data!$A:$A,"COGS_IMPORT",Data!$G:$G) -> -48800 | G8: =-SUMIF(Data!$A:$A,"COGS_IMPORT",Data!$H:$H) -> -1569799.8 | H8: =SUM(C8:G8) -> -4306433.5
A9: Personnel | C9: =-SUMIF(Data!$A:$A,"OPEX_PAYROLL",Data!$D:$D) -> -652355 | D9: =-SUMIF(Data!$A:$A,"OPEX_PAYROLL",Data!$E:$E) -> -721554.41 | E9: =-SUMIF(Data!$A:$A,"OPEX_PAYROLL",Data!$F:$F) -> -847586.51 | F9: =-SUMIF(Data!$A:$A,"OPEX_PAYROLL",Data!$G:$G) -> -1027262.9 | G9: =-SUMIF(Data!$A:$A,"OPEX_PAYROLL",Data!$H:$H) -> -1121320 | H9: =SUM(C9:G9) -> -4370078.9
A10: Rent & utilities | C10: =-SUMIF(Data!$A:$A,"OPEX_RENT",Data!$D:$D) -> -69601.59 | D10: =-SUMIF(Data!$A:$A,"OPEX_RENT",Data!$E:$E) -> -62454.74 | E10: =-SUMIF(Data!$A:$A,"OPEX_RENT",Data!$F:$F) -> -60442.98 | F10: =-SUMIF(Data!$A:$A,"OPEX_RENT",Data!$G:$G) -> -29852.02 | G10: =-SUMIF(Data!$A:$A,"OPEX_RENT",Data!$H:$H) -> -41506.97 | H10: =SUM(C10:G10) -> -263858.3
A11: Marketing & transport | C11: =-SUMIF(Data!$A:$A,"OPEX_MKT",Data!$D:$D) -> -20000 | D11: =-SUMIF(Data!$A:$A,"OPEX_MKT",Data!$E:$E) -> -2400 | E11: =-SUMIF(Data!$A:$A,"OPEX_MKT",Data!$F:$F) -> -69486 | F11: =-SUMIF(Data!$A:$A,"OPEX_MKT",Data!$G:$G) -> -80237 | G11: =-SUMIF(Data!$A:$A,"OPEX_MKT",Data!$H:$H) -> -55814 | H11: =SUM(C11:G11) -> -227937
A12: Bank charges | C12: =-SUMIF(Data!$A:$A,"OPEX_BANK",Data!$D:$D) -> -35150.97 | D12: =-SUMIF(Data!$A:$A,"OPEX_BANK",Data!$E:$E) -> -23119.07 | E12: =-SUMIF(Data!$A:$A,"OPEX_BANK",Data!$F:$F) -> -31670.83 | F12: =-SUMIF(Data!$A:$A,"OPEX_BANK",Data!$G:$G) -> -53610.61 | G12: =-SUMIF(Data!$A:$A,"OPEX_BANK",Data!$H:$H) -> -47713.27 | H12: =SUM(C12:G12) -> -191264.75
A13: Services & subscriptions | C13: =-SUMIF(Data!$A:$A,"OPEX_SERV",Data!$D:$D) -> -41300 | D13: =-SUMIF(Data!$A:$A,"OPEX_SERV",Data!$E:$E) -> -112422 | E13: =-SUMIF(Data!$A:$A,"OPEX_SERV",Data!$F:$F) -> -50809 | F13: =-SUMIF(Data!$A:$A,"OPEX_SERV",Data!$G:$G) -> -45126.62 | G13: =-SUMIF(Data!$A:$A,"OPEX_SERV",Data!$H:$H) -> -10180 | H13: =SUM(C13:G13) -> -259837.62
A14: Market consumables | C14: =-SUMIF(Data!$A:$A,"OPEX_CONS",Data!$D:$D) -> -6950 | D14: =-SUMIF(Data!$A:$A,"OPEX_CONS",Data!$E:$E) -> -36155 | E14: =-SUMIF(Data!$A:$A,"OPEX_CONS",Data!$F:$F) -> -4180 | F14: =-SUMIF(Data!$A:$A,"OPEX_CONS",Data!$G:$G) -> -5530 | G14: =-SUMIF(Data!$A:$A,"OPEX_CONS",Data!$H:$H) -> -1760 | H14: =SUM(C14:G14) -> -54575
A15: Unified (simplified) tax | C15: =-SUMIF(Data!$A:$A,"TAX",Data!$D:$D) -> -92671 | D15: =-SUMIF(Data!$A:$A,"TAX",Data!$E:$E) -> -100020 | E15: =-SUMIF(Data!$A:$A,"TAX",Data!$F:$F) -> -248968.44 | F15: =-SUMIF(Data!$A:$A,"TAX",Data!$G:$G) -> -145209.77 | G15: =-SUMIF(Data!$A:$A,"TAX",Data!$H:$H) -> -154846.41 | H15: =SUM(C15:G15) -> -741715.62
A16: Other non-operating (travel, fines, advances) | C16: =-SUMIF(Data!$A:$A,"NONOP_OTHER",Data!$D:$D) -> 0 | D16: =-SUMIF(Data!$A:$A,"NONOP_OTHER",Data!$E:$E) -> -20000 | E16: =-SUMIF(Data!$A:$A,"NONOP_OTHER",Data!$F:$F) -> -5000 | F16: =-SUMIF(Data!$A:$A,"NONOP_OTHER",Data!$G:$G) -> -152000 | G16: =-SUMIF(Data!$A:$A,"NONOP_OTHER",Data!$H:$H) -> -25000 | H16: =SUM(C16:G16) -> -202000
A17: Unclassified payments ('?') | C17: =-SUMIF(Data!$A:$A,"NONOP_UNCL",Data!$D:$D) -> 0 | D17: =-SUMIF(Data!$A:$A,"NONOP_UNCL",Data!$E:$E) -> -131660 | E17: =-SUMIF(Data!$A:$A,"NONOP_UNCL",Data!$F:$F) -> -9600 | F17: =-SUMIF(Data!$A:$A,"NONOP_UNCL",Data!$G:$G) -> -2120 | G17: =-SUMIF(Data!$A:$A,"NONOP_UNCL",Data!$H:$H) -> -660 | H17: =SUM(C17:G17) -> -144040
A18: Net cash from operating activities | C18: =C6+C7+C8+C9+C10+C11+C12+C13+C14+C15+C16+C17 -> 621646.08 | D18: =D6+D7+D8+D9+D10+D11+D12+D13+D14+D15+D16+D17 -> -2594168.9 | E18: =E6+E7+E8+E9+E10+E11+E12+E13+E14+E15+E16+E17 -> 755534.14 | F18: =F6+F7+F8+F9+F10+F11+F12+F13+F14+F15+F16+F17 -> 707777.21 | G18: =G6+G7+G8+G9+G10+G11+G12+G13+G14+G15+G16+G17 -> 2000111 | H18: =SUM(C18:G18) -> 1490899.5
A20: INVESTING ACTIVITIES
A21: Capital expenditure (equipment, fixed assets, software, renovation) | C21: =-SUMIF(Data!$A:$A,"CAPEX",Data!$D:$D) -> -12000 | D21: =-SUMIF(Data!$A:$A,"CAPEX",Data!$E:$E) -> -41118 | E21: =-SUMIF(Data!$A:$A,"CAPEX",Data!$F:$F) -> -263563 | F21: =-SUMIF(Data!$A:$A,"CAPEX",Data!$G:$G) -> -196000 | G21: =-SUMIF(Data!$A:$A,"CAPEX",Data!$H:$H) -> -105950 | H21: =SUM(C21:G21) -> -618631
A22: Net cash used in investing activities | C22: =C21 -> -12000 | D22: =D21 -> -41118 | E22: =E21 -> -263563 | F22: =F21 -> -196000 | G22: =G21 -> -105950 | H22: =SUM(C22:G22) -> -618631
A24: FINANCING ACTIVITIES
A25: Capital injections (KGS) | C25: =SUMIF(Data!$A:$A,"FIN_INJECT",Data!$D:$D) -> 0 | D25: =SUMIF(Data!$A:$A,"FIN_INJECT",Data!$E:$E) -> 2000000 | E25: =SUMIF(Data!$A:$A,"FIN_INJECT",Data!$F:$F) -> 599640 | F25: =SUMIF(Data!$A:$A,"FIN_INJECT",Data!$G:$G) -> 0 | G25: =SUMIF(Data!$A:$A,"FIN_INJECT",Data!$H:$H) -> 0 | H25: =SUM(C25:G25) -> 2599640
A26: Owner drawings | C26: =-SUMIF(Data!$A:$A,"FIN_DRAW",Data!$D:$D) -> 0 | D26: =-SUMIF(Data!$A:$A,"FIN_DRAW",Data!$E:$E) -> -135000 | E26: =-SUMIF(Data!$A:$A,"FIN_DRAW",Data!$F:$F) -> -1101540 | F26: =-SUMIF(Data!$A:$A,"FIN_DRAW",Data!$G:$G) -> -700000 | G26: =-SUMIF(Data!$A:$A,"FIN_DRAW",Data!$H:$H) -> -400000 | H26: =SUM(C26:G26) -> -2336540
A27: Net cash from financing activities | C27: =C25+C26 -> 0 | D27: =D25+D26 -> 1865000 | E27: =E25+E26 -> -501900 | F27: =F25+F26 -> -700000 | G27: =G25+G26 -> -400000 | H27: =SUM(C27:G27) -> 263100
A29: NET CHANGE IN CASH | C29: =C18+C22+C27 -> 609646.08 | D29: =D18+D22+D27 -> -770286.94 | E29: =E18+E22+E27 -> -9928.86 | F29: =F18+F22+F27 -> -188222.79 | G29: =G18+G22+G27 -> 1494161 | H29: =SUM(C29:G29) -> 1135368.5
A31: Tie-out: Net change in cash should equal the source workbook's own net line (+1,135,368 YTD).

Sheet Data
A1: GAMMA — Source data (cash movements), Jan–May 2026
A2: All values in KGS. Blue = transcribed inputs from cashflow_2026_gamma.xlsx (Лист1). '*' rows are memo items tracked outside the company's net-cash line.
A4: Group | B4: Line item (EN) | C4: Line item (RU) | D4: Jan-26 | E4: Feb-26 | F4: Mar-26 | G4: Apr-26 | H4: May-26 | I4: YTD
A5: REV_RETAIL | B5: Retail POS — Mbank | C5: Касса Мбанк | D5: 1013424.6 | E5: 1098719.8 | F5: 1071167.9 | G5: 1452822.2 | H5: 1839217.5 | I5: =SUM(D5:H5) -> 6475351.9
A6: REV_RETAIL | B6: Retail POS — Optima | C6: Касса Оптима | D6: 734024.5 | E6: 643994.22 | F6: 1508004 | G6: 1870615 | H6: 2085644 | I6: =SUM(D6:H6) -> 6842281.7
A7: REV_RETAIL | B7: Retail cash — Kokzhar | C7: Касса Наличные Кокжар | D7: 949126.68 | E7: 937578.51 | F7: 1127234.6 | G7: 1523725 | H7: 1607576.8 | I7: =SUM(D7:H7) -> 6145241.6
A8: REV_RETAIL | B8: Retail cash — Belovodsk | C8: Касса Наличные Беловодск | D8: 0 | E8: 0 | F8: 79597 | G8: 270890.41 | H8: 265065.62 | I8: =SUM(D8:H8) -> 615553.03
A9: REV_B2B | B9: Wholesale B2B — bank | C9: B2B Банк | D9: 766665.4 | E9: 614435.7 | F9: 1890097.9 | G9: 1091807.4 | H9: 1688746.7 | I9: =SUM(D9:H9) -> 6051753.1
A10: REV_B2B | B10: Wholesale B2B — cash | C10: B2B Наличные | D10: 9920 | E10: 30845 | F10: 0 | G10: 10968 | H10: 63254 | I10: =SUM(D10:H10) -> 114987
A11: REV_OTHER | B11: Sublease — bank | C11: Субаренда банк | D11: 15000 | E11: 5000 | F11: 10000 | G11: 10000 | H11: 0 | I11: =SUM(D11:H11) -> 40000
A12: REV_OTHER | B12: Sublease — cash | C12: Субаренда наличные | D12: 6000 | E12: 6000 | F12: 6000 | G12: 6000 | H12: 6000 | I12: =SUM(D12:H12) -> 30000
A13: REV_OTHER | B13: Recycling / scrap paper | C13: Макулатура | D13: 0 | E13: 6155 | F13: 292075 | G13: 9600 | H13: 31377 | I13: =SUM(D13:H13) -> 339207
A14: COGS_SUP | B14: Payments to suppliers (goods) | C14: Оплаты поставщикам | D14: 1930393.5 | E14: 2685411.3 | F14: 3278858.5 | G14: 3948901.8 | H14: 2558170.1 | I14: =SUM(D14:H14) -> 14401735
A15: COGS_IMPORT | B15: Logistics (Li Group) | C15: Ли групп (логистика) | D15: 0 | E15: 0 | F15: 597040 | G15: 0 | H15: 0 | I15: =SUM(D15:H15) -> 597040
A16: COGS_IMPORT | B16: HS-code (NY Lingua) | C16: Нью-Йорк Лингва (ТНВЭД) | D16: 0 | E16: 6800 | F16: 0 | G16: 0 | H16: 0 | I16: =SUM(D16:H16) -> 6800
... A80: MEMO | B80: Cashier surplus* | C80: Излишки кассира* | D80: 48.42 | E80: 0 | F80: 7.47 | G80: 383.08 | H80: 361.39 | I80: =SUM(D80:H80) -> 800.36

Sheet Notes
A1: Notes & assumptions
A3: 1. Basis. The source file is a daily CASH tracker, so these statements are prepared on a CASH basis (receipts and payments), not accrual. There is no inventory, accruals, receivables/payables or depreciation data, so 'Cost of sales' = cash paid to suppliers + import/customs costs in the period, and there is no D&A line.
A5: 2. Period. Actuals exist for January–May 2026 only; June–December in the source are empty and are excluded. 'YTD' = Jan–May 2026.
A7: 3. Currency. All figures in KGS (Kyrgyz som). USD/tenge-denominated rows in the source are flagged '*' and shown only as memo items.
A9: 4. Reconciliation. Net change in cash (+1,135,368 YTD) equals the source workbook's own net line, which is Total income − Total expenses + KGS capital injections.
A11: 5. Cost of sales includes import VAT (НДС на импорт). If this VAT is recoverable, reclassify it out of cost of sales to a VAT receivable.
A13: 6. Capital expenditure (РАЗОВЫЕ ДОРАБОТКИ И ВЛОЖЕНИЯ — equipment, fixed-asset purchases, renovation, software/site development) is treated as INVESTING, not a P&L expense. Under accrual accounting it would be capitalised and depreciated.
A15: 7. Owner drawings (the 'вывод' rows: Esenbaev, IP Rakhmanov, IP Avtandil) are treated as FINANCING distributions, not expenses. Capital injections ('инвестиции сом') are FINANCING inflows.
A17: 8. 'Unclassified payments' (rows marked '?' in the source: RM Plus, DAS Group, IP Loparev, Saparbekova, Brave) are kept in non-operating pending classification — reassign to cost of sales, opex or drawings once their nature is known.
A19: 9. Unified tax (единый налог) is Kyrgyzstan's simplified turnover-based tax; it is shown below EBITDA as the period tax charge.
A21: 10. Memo items (USD injections, USD 'global', tenge 'Mir Instrumentov', cashier shortages/surpluses) sit outside the source's net-cash line and are excluded here; 'Mir Instrumentov' (KZT 2.58m) may in fact be a supplier purchase — confirm and reclassify to cost of sales if so.
A23: 11. All amounts flow from the 'Data' sheet via SUMIF; edit a value there and the P&L and Cash Flow update on recalculation.
